django_multisite_plus/__init__.py
django_multisite_plus/admin.py
django_multisite_plus/apps.py
django_multisite_plus/cli.py
django_multisite_plus/cms_urls.py
django_multisite_plus/conf.py
django_multisite_plus/constants.py
django_multisite_plus/fastrouter_lookup.py
django_multisite_plus/middlewares.py
django_multisite_plus/models.py
django_multisite_plus/migrations/0001_initial.py
django_multisite_plus/migrations/0002_auto_20180125_1157.py
django_multisite_plus/migrations/__init__.py
django_multisite_plus-0.6.3.dist-info/METADATA
django_multisite_plus-0.6.3.dist-info/RECORD
django_multisite_plus-0.6.3.dist-info/WHEEL
django_multisite_plus-0.6.3.dist-info/entry_points.txt
django_multisite_plus-0.6.3.dist-info/top_level.txt
