Metadata-Version: 2.1
Name: django-multisite-plus
Version: 0.6.3
Summary: An extension to django-multisite that eases local development.
Home-page: https://github.com/divio/django-multisite-plus
Author: Divio AG
Author-email: info@divio.com
License: BSD
Platform: UNKNOWN
Classifier: Development Status :: 5 - Production/Stable
Classifier: Environment :: Web Environment
Classifier: Framework :: Django
Classifier: Intended Audience :: Developers
Classifier: License :: OSI Approved :: BSD License
Classifier: Operating System :: OS Independent
Classifier: Programming Language :: Python
Classifier: Programming Language :: Python :: 2
Classifier: Programming Language :: Python :: 2.7
Classifier: Programming Language :: Python :: 3
Classifier: Programming Language :: Python :: 3.4
Classifier: Programming Language :: Python :: 3.5
Classifier: Topic :: Internet :: WWW/HTTP
Classifier: Topic :: Internet :: WWW/HTTP :: Dynamic Content
Classifier: Topic :: Software Development :: Libraries :: Application Frameworks
Classifier: Topic :: Software Development :: Libraries :: Python Modules
Requires-Dist: Django (<2.0,>=1.8)
Requires-Dist: django-multisite (>=1.4.0)
Requires-Dist: djangocms-multisite (>=0.2.2)
Requires-Dist: aldryn-addons
Requires-Dist: click
Requires-Dist: psycopg2 (>=2.5)
Requires-Dist: yurl
